{
  "type": "morning",
  "date": "2026-05-15",
  "generatedAt": "2026-05-15T06:00:11.231+09:00",
  "lead": "",
  "topStory": {
    "title": "選挙動画、AI生成を明示義務付けへ 今国会で法整備",
    "body": "選挙運動におけるインターネット広告の規制強化に向け、与野党は、AI（人工知能）によって生成された動画であることを明示する義務を投稿者に課す方針で合意した。今国会での法整備を目指す。\n\nこの規制は、AI技術の急速な発展に伴い、偽情報や誤解を招くコンテンツが選挙に与える影響への懸念が高まっていることを受けて導入される。特に、AIが生成した映像や音声は、現実には存在しない出来事をあたかも真実であるかのように見せかけることが可能であり、有権者の判断を誤らせるリスクが指摘されている。\n\n具体的には、選挙運動期間中に公開される動画広告について、AIによって生成された部分がある場合には、その旨を視聴者に分かりやすく表示することを義務付ける。これにより、有権者は情報源をより正確に認識し、批判的な視点を持って情報に接することができるようになることが期待される。\n\n今回の合意は、自由民主党、立憲民主党をはじめとする主要政党間でなされたもので、速やかな法案提出と審議入りを目指している。インターネット広告は、従来のテレビCMなどに比べて低コストで広範囲に情報発信が可能であるため、選挙運動におけるその重要性は増している。しかし、その一方で、規制が追いついていない側面も課題となっていた。\n\n今回の法整備により、AI生成コンテンツの透明性が確保され、より公正で健全な選挙の実現に寄与することが期待される。今後、具体的な表示方法や違反した場合の罰則なども含めた詳細な規定が議論される見通しだ。",
    "topicId": "ai_tech",
    "topicName": "AI・プログラミング",
    "color": "#7c3aed",
    "references": [
      {
        "title": "選挙動画「AI生成」を明示 投稿者に義務付け 与野党が合意、今国会で法整備 - 日本経済新聞",
        "url": "https://news.google.com/rss/articles/CBMibEFVX3lxTFBlTEs4c2FlNm9HSmxscXR5ZmFsWkNYM013M0thUUxlTjVsZzVnUEZqbTlla3BaQl9FbzBHRVpTaXpqN2ozX1E2RW5VNmhDVmJ0R1RrWVJkRFNUNVE5MjNLN1BiNkJxdk5pZS0zaQ?oc=5",
        "source": "Google: 生成AI",
        "topicId": "ai_tech"
      }
    ]
  },
  "midStories": [],
  "briefs": []
}